quickics/__init__.py
QuickICS-0.0.5.dist-info/LICENSE.txt
QuickICS-0.0.5.dist-info/METADATA
QuickICS-0.0.5.dist-info/WHEEL
QuickICS-0.0.5.dist-info/top_level.txt
QuickICS-0.0.5.dist-info/RECORD
